kadalu_content_apis/__init__.py
kadalu_content_apis/folders.py
kadalu_content_apis/helpers.py
kadalu_content_apis/objects.py
kadalu_content_apis/regions.py
kadalu_content_apis/shares.py
kadalu_content_apis/templates.py
kadalu_content_apis/version.py
kadalu_content_apis-1.0.dist-info/METADATA
kadalu_content_apis-1.0.dist-info/WHEEL
kadalu_content_apis-1.0.dist-info/top_level.txt
kadalu_content_apis-1.0.dist-info/RECORD
