Metadata-Version: 2.1
Name: kadalu-content-apis
Version: 1.0
Home-page: https://github.com/kadalu-tech/content-apis-sdk
Author: Kadalu Technologies Private Limited
Author-email: packages@kadalu.tech
License: GPL-v3
Keywords: kadalu content apis
Classifier: Development Status :: 5 - Production/Stable
Classifier: Programming Language :: Python :: 3
Classifier: Programming Language :: Python :: 3 :: Only
Requires-Dist: urllib3
